LICENSE.txt
README.md
dlt/__init__.py
dlt/__main__.py
dlt/cli/__init__.py
dlt/cli/_dlt.py
dlt/cli/config_toml_writer.py
dlt/cli/deploy_command.py
dlt/cli/deploy_command_helpers.py
dlt/cli/echo.py
dlt/cli/exceptions.py
dlt/cli/init_command.py
dlt/cli/pipeline_command.py
dlt/cli/pipeline_files.py
dlt/cli/requirements.py
dlt/cli/source_detection.py
dlt/cli/telemetry_command.py
dlt/cli/utils.py
dlt/common/__init__.py
dlt/common/arithmetics.py
dlt/common/configuration/__init__.py
dlt/common/configuration/accessors.py
dlt/common/configuration/container.py
dlt/common/configuration/exceptions.py
dlt/common/configuration/inject.py
dlt/common/configuration/paths.py
dlt/common/configuration/providers/__init__.py
dlt/common/configuration/providers/airflow.py
dlt/common/configuration/providers/context.py
dlt/common/configuration/providers/dictionary.py
dlt/common/configuration/providers/environ.py
dlt/common/configuration/providers/google_secrets.py
dlt/common/configuration/providers/provider.py
dlt/common/configuration/providers/toml.py
dlt/common/configuration/providers/vault.py
dlt/common/configuration/resolve.py
dlt/common/configuration/specs/__init__.py
dlt/common/configuration/specs/api_credentials.py
dlt/common/configuration/specs/aws_credentials.py
dlt/common/configuration/specs/azure_credentials.py
dlt/common/configuration/specs/base_configuration.py
dlt/common/configuration/specs/config_providers_context.py
dlt/common/configuration/specs/config_section_context.py
dlt/common/configuration/specs/connection_string_credentials.py
dlt/common/configuration/specs/exceptions.py
dlt/common/configuration/specs/gcp_credentials.py
dlt/common/configuration/specs/known_sections.py
dlt/common/configuration/specs/run_configuration.py
dlt/common/configuration/utils.py
dlt/common/data_types/__init__.py
dlt/common/data_types/type_helpers.py
dlt/common/data_types/typing.py
dlt/common/data_writers/__init__.py
dlt/common/data_writers/buffered.py
dlt/common/data_writers/configuration.py
dlt_dataops-0.5.4a0.dist-info/LICENSE.txt
dlt_dataops-0.5.4a0.dist-info/METADATA
dlt_dataops-0.5.4a0.dist-info/WHEEL
dlt_dataops-0.5.4a0.dist-info/entry_points.txt
dlt_dataops-0.5.4a0.dist-info/RECORD
