Metadata-Version: 2.1
Name: dlt-dataops
Version: 0.5.4a0
Summary: dlt is an open-source python-first scalable data loading library that does not require any backend to run.
Home-page: https://github.com/dlt-hub
License: Apache-2.0
Keywords: etl
Author: dltHub Inc.
Author-email: services@dlthub.com
Maintainer: Marcin Rudolf
Maintainer-email: marcin@dlthub.com
Requires-Python: >=3.8.1,<3.13
Classifier: Development Status :: 4 - Beta
Classifier: Intended Audience :: Developers
Classifier: License :: OSI Approved :: Apache Software License
Classifier: Operating System :: MacOS :: MacOS X
Classifier: Operating System :: Microsoft :: Windows
Classifier: Operating System :: POSIX :: Linux
Classifier: Programming Language :: Python :: 3
Classifier: Programming Language :: Python :: 3.9
Classifier: Programming Language :: Python :: 3.10
Classifier: Programming Language :: Python :: 3.11
Classifier: Programming Language :: Python :: 3.12
Classifier: Topic :: Software Development :: Libraries
Classifier: Typing :: Typed
Provides-Extra: athena
Provides-Extra: az
Provides-Extra: bigquery
Provides-Extra: cli
Provides-Extra: clickhouse
Provides-Extra: databricks
Provides-Extra: deltalake
Provides-Extra: dremio
Provides-Extra: duckdb
Provides-Extra: filesystem
Provides-Extra: gcp
Provides-Extra: gs
Provides-Extra: lancedb
Provides-Extra: motherduck
Provides-Extra: mssql
Provides-Extra: parquet
Provides-Extra: postgres
Provides-Extra: qdrant
Provides-Extra: redshift
Provides-Extra: s3
Provides-Extra: snowflake
Provides-Extra: synapse
Provides-Extra: weaviate
Requires-Dist: PyYAML (>=5.4.1)
Requires-Dist: adlfs (>=2022.4.0) ; extra == "az" or extra == "synapse" or extra == "clickhouse"
Requires-Dist: astunparse (>=1.6.3)
Requires-Dist: botocore (>=1.28) ; extra == "filesystem" or extra == "s3" or extra == "athena"
Requires-Dist: click (>=7.1)
Requires-Dist: clickhouse-connect (>=0.7.7) ; extra == "clickhouse"
Requires-Dist: clickhouse-driver (>=0.2.7) ; extra == "clickhouse"
Requires-Dist: cron-descriptor (>=1.2.32) ; extra == "cli"
Requires-Dist: databricks-sql-connector (>=2.9.3) ; extra == "databricks"
Requires-Dist: deltalake (>=0.17.4) ; extra == "deltalake"
Requires-Dist: duckdb (>=0.6.1,<0.11) ; extra == "duckdb" or extra == "motherduck"
Requires-Dist: fsspec (>=2022.4.0)
Requires-Dist: gcsfs (>=2022.4.0) ; extra == "gcp" or extra == "bigquery" or extra == "gs" or extra == "clickhouse"
Requires-Dist: gitpython (>=3.1.29)
Requires-Dist: giturlparse (>=0.10.0)
Requires-Dist: google-cloud-bigquery (>=2.26.0) ; extra == "gcp" or extra == "bigquery"
Requires-Dist: grpcio (>=1.50.0) ; extra == "gcp" or extra == "bigquery"
Requires-Dist: hexbytes (>=0.2.2)
Requires-Dist: humanize (>=4.4.0)
Requires-Dist: jsonpath-ng (>=1.5.3)
Requires-Dist: lancedb (>=0.8.2) ; (python_version >= "3.9") and (extra == "lancedb")
Requires-Dist: makefun (>=1.15.0)
Requires-Dist: orjson (>=3.6.7,<4,!=3.9.11,!=3.9.12,!=3.9.13,!=3.9.14,!=3.10.1) ; platform_python_implementation != "PyPy"
Requires-Dist: packaging (>=21.1)
Requires-Dist: pathvalidate (>=2.5.2)
Requires-Dist: pendulum (>=2.1.2)
Requires-Dist: pipdeptree (>=2.9.0,<2.10) ; extra == "cli"
Requires-Dist: psycopg2-binary (>=2.9.1) ; extra == "postgres" or extra == "redshift"
Requires-Dist: psycopg2cffi (>=2.9.0) ; (platform_python_implementation == "PyPy") and (extra == "postgres" or extra == "redshift")
Requires-Dist: pyarrow (>=12.0.0) ; extra == "bigquery" or extra == "parquet" or extra == "motherduck" or extra == "athena" or extra == "synapse" or extra == "clickhouse" or extra == "dremio" or extra == "lancedb" or extra == "deltalake"
Requires-Dist: pyathena (>=2.9.6) ; extra == "athena"
Requires-Dist: pyodbc (>=4.0.39) ; extra == "mssql" or extra == "synapse"
Requires-Dist: pytz (>=2022.6)
Requires-Dist: qdrant-client[fastembed] (>=1.8) ; extra == "qdrant"
Requires-Dist: requests (>=2.26.0)
Requires-Dist: requirements-parser (>=0.5.0)
Requires-Dist: s3fs (>=2022.4.0) ; extra == "filesystem" or extra == "s3" or extra == "athena" or extra == "clickhouse"
Requires-Dist: semver (>=2.13.0)
Requires-Dist: setuptools (>=65.6.0)
Requires-Dist: simplejson (>=3.17.5)
Requires-Dist: snowflake-connector-python (>=3.5.0) ; extra == "snowflake"
Requires-Dist: tenacity (>=8.0.2)
Requires-Dist: tomlkit (>=0.11.3)
Requires-Dist: typing-extensions (>=4.0.0)
Requires-Dist: tzdata (>=2022.1)
Requires-Dist: weaviate-client (>=3.22) ; extra == "weaviate"
Requires-Dist: win-precise-time (>=1.4.2) ; os_name == "nt"
Project-URL: Repository, https://github.com/dlt-hub/dlt
